{
  "@context": {
    "dcterms": "http://purl.org/dc/terms/",
    "people": "http://lblod.github.io/editor/assets/people.json#",
    "gemeente": "http://codex.vlaanderen.be/Zoeken/Document.aspx?DID=1013949&param=inhoud&AID=",
    "lbld": "http://decisions.data.vlaanderen.be/ns#",
    "mandaat": "http://mandates.data.vlaanderen.be/ns#",
    "schema": "http://schema.org/",
    "xsd": "http://www.w3.org/2001/XMLSchema#"
  },
  "@graph": [{
    "@type": "schema:Person",
    "@id": "people:bart",
    "schema:name": "Bart Caron"
  }, {
    "@type": "schema:Person",
    "@id": "people:mattias",
    "schema:name": "Mattias Vandemaele"
  }, {
    "@type": "schema:Person",
    "@id": "people:petra",
    "schema:name": "Petra Verhenne"
  }, {
    "@type": "schema:Person",
    "@id": "people:stijn",
    "schema:name": "Stijn Vanneste"
  }, {
    "@type": "schema:Person",
    "@id": "people:annelies",
    "schema:name": "Annelies Vandendriesche"
  }, {
    "@type": "schema:Person",
    "@id": "people:jan",
    "schema:name": "Jan Vansteenlandt"
  }, {
    "@type": "schema:Person",
    "@id": "people:ingrid",
    "schema:name": "Ingrid Willems"
  }, {
    "@type": "schema:Person",
    "@id": "people:pieter",
    "schema:name": "Pieter Colpaert"
  }, {
    "@type": "schema:Person",
    "@id": "people:katrien",
    "schema:name": "Katrien De Smet"
  }, {
    "@type": "schema:Person",
    "@id": "people:peter",
    "schema:name": "Peter Mechant"
  }, {
    "@type": "schema:Person",
    "@id": "people:heidi",
    "schema:name": "Heidi Godderis"
  }, {
    "@type": "schema:Person",
    "@id": "people:raf",
    "schema:name": "Raf Buyle"
  }, {
    "@type": "schema:Person",
    "@id": "people:liesbeth",
    "schema:name": "Liesbeth De Clercq"
  }, {
    "@type": "schema:Person",
    "@id": "people:geert",
    "schema:name": "Geert Van Campenhout"
  }, {
    "@type": "schema:Person",
    "@id": "people:carolien",
    "schema:name": "Carolien Willen"
  }, {
    "@type": "schema:Person",
    "@id": "people:katie",
    "schema:name": "Katie Heyse"
  }, {
    "@type": "schema:Person",
    "@id": "people:thomas",
    "schema:name": "Thomas Ghysels"
  }, {
    "@type": "schema:Person",
    "@id": "people:joep",
    "schema:name": "Joep Luijten"
  }, {
    "@type": "schema:Person",
    "@id": "people:veronique",
    "schema:name": "Veronique Volders"
  }, {
    "@type": "schema:Person",
    "@id": "people:mathias",
    "schema:name": "Mathias Van Compernolle"
  }]
}
